CHANGES.txt
LICENSE.txt
MANIFEST.in
README.txt
setup.cfg
setup.py
bin/__init__.py
bin/flashstudy.py
flashCardStudy.egg-info/PKG-INFO
flashCardStudy.egg-info/SOURCES.txt
flashCardStudy.egg-info/dependency_links.txt
flashCardStudy.egg-info/entry_points.txt
flashCardStudy.egg-info/requires.txt
flashCardStudy.egg-info/top_level.txt
flashcardstudy/__init__.py
flashcardstudy/card.py
flashcardstudy/cliparser.py
flashcardstudy/content.py
flashcardstudy/display.py
flashcardstudy/errors.py
flashcardstudy/help.py
flashcardstudy/processor.py
flashcardstudy/sfile.py
flashcardstudy/stack.py
gui/__init__.py
gui/about.py
gui/config.py
gui/display.py
gui/main.py
tests/__init__.py
tests/cli_tests.py
tests/content_tests.py