Metadata-Version: 1.1
Name: flashCardStudy
Version: 1.0.6
Summary: multi-platform GUI and CLI based program for memorizing and studying
Home-page: https://github.com/comatory/flashCardStudy
Author: Ondrej Synacek
Author-email: osekdomains@gmail.com
License: LICENSE.txt
Platform: UNKNOWN
Classifier: Programming Language :: Python
Classifier: Programming Language :: Python :: 2.7
Classifier: License :: OSI Approved :: MIT License
Classifier: Topic :: Education
